<?xml version="1.0" encoding="UTF-8"?><index key="268436239">
<marker id="528941057"/>
<marker id="528941063"/>
<marker id="528941064"/>
<marker id="528941065"/>
<marker id="528941066"/>
<marker id="528941068"/>
<marker id="528941069"/>
<marker id="528941070"/>
<marker id="528941071"/>
<marker id="528941072"/>
<marker id="528941073"/>
<marker id="528941126"/>
<marker id="528941127"/>
<marker id="528941152"/>
<marker id="528941153"/>
<marker id="528941154"/>
<marker id="1273061376"/>
<marker id="1273061377"/>
<marker id="1273061378"/>
<marker id="1273061379"/>
<marker id="1273061380"/>
<marker id="1273061381"/>
<marker id="1273061382"/>
<marker id="1273061383"/>
<marker id="1273061384"/>
<marker id="1273061385"/>
<marker id="1273061386"/>
<marker id="1273061387"/>
<marker id="1273061388"/>
<marker id="1273061389"/>
<marker id="1273061390"/>
<marker id="1273061391"/>
<marker id="1273061392"/>
<marker id="1273065472"/>
<marker id="1273065473"/>
<marker id="1273065474"/>
<marker id="1273065475"/>
<marker id="1273065476"/>
<marker id="1273131019"/>
<marker id="1273131020"/>
<marker id="1273131021"/>
<marker id="1273131022"/>
<marker id="1273131023"/>
<marker id="1273131024"/>
<marker id="1273131025"/>
<marker id="1273131026"/>
<marker id="1273131027"/>
<marker id="1273131028"/>
<marker id="1273131029"/>
<marker id="1273131030"/>
<marker id="1273131031"/>
<marker id="1273131032"/>
<marker id="1273131033"/>
<marker id="1273131034"/>
<marker id="1273131035"/>
<marker id="1273131036"/>
<marker id="1273131037"/>
<marker id="1273131038"/>
<marker id="1273131039"/>
<marker id="1273131040"/>
<marker id="1273131041"/>
<marker id="1273131042"/>
<marker id="1273131043"/>
<marker id="1273131044"/>
<marker id="1273131045"/>
<marker id="1273131046"/>
<marker id="1273131047"/>
<marker id="1273131048"/>
<marker id="1273131049"/>
<marker id="1273131050"/>
<marker id="1273131051"/>
<marker id="1273131052"/>
<marker id="1273131053"/>
<marker id="1273131054"/>
<marker id="1273131055"/>
<marker id="1273131056"/>
<marker id="1273131057"/>
<marker id="1273131058"/>
<marker id="1273131059"/>
<marker id="1273131060"/>
<marker id="1273131061"/>
<marker id="1273131062"/>
<marker id="1273131063"/>
<marker id="1273131064"/>
<marker id="1273131065"/>
<marker id="1273131066"/>
<marker id="1273131067"/>
<marker id="1273131068"/>
<marker id="1273131069"/>
<marker id="1273131070"/>
<marker id="1273131071"/>
<marker id="1273131072"/>
<marker id="1273131073"/>
<marker id="1273131074"/>
<marker id="1273131075"/>
<marker id="1273131076"/>
<marker id="1273131077"/>
<marker id="1273131078"/>
<marker id="1273131079"/>
<marker id="1273131080"/>
<marker id="1273131081"/>
<marker id="1273131082"/>
<marker id="1273131083"/>
<marker id="1273131084"/>
<marker id="1273131087"/>
<marker id="1273131088"/>
<marker id="1273131089"/>
<marker id="1273131090"/>
<marker id="1273131091"/>
<marker id="1273131092"/>
<marker id="1273131093"/>
<marker id="1273131094"/>
<marker id="1273131095"/>
<marker id="1273131096"/>
<marker id="1273131097"/>
<marker id="1273131098"/>
<marker id="1273131099"/>
<marker id="1273131100"/>
<marker id="1273131101"/>
<marker id="1273131102"/>
<marker id="1273131103"/>
<marker id="1273131104"/>
<marker id="1273131105"/>
<marker id="1273131106"/>
<marker id="1273131109"/>
<marker id="1273135113"/>
<marker id="1273135114"/>
<marker id="1273135115"/>
<marker id="1273135116"/>
<marker id="1273135117"/>
<marker id="1273135118"/>
<marker id="1273135119"/>
<marker id="1273135120"/>
<marker id="1273135121"/>
<marker id="1273135122"/>
<marker id="1273139218"/>
<marker id="1273139219"/>
<marker id="1273139220"/>
<marker id="1273139221"/>
<marker id="1273139222"/>
<marker id="1273139223"/>
<marker id="1273139225"/>
<marker id="1273139226"/>
<marker id="1273139227"/>
<marker id="1273143302"/>
<marker id="1273143303"/>
<marker id="1273143304"/>
<marker id="1273143305"/>
<marker id="1273143306"/>
<marker id="1273143307"/>
<marker id="1273143308"/>
<marker id="1273143309"/>
<marker id="1273143310"/>
<marker id="1273143311"/>
<marker id="1273143312"/>
<marker id="1273143313"/>
<marker id="1273143314"/>
<marker id="1273143315"/>
<marker id="1273196545"/>
<marker id="1273196546"/>
<marker id="1273196547"/>
<marker id="1273196548"/>
<marker id="1273196549"/>
<marker id="1273196550"/>
<marker id="1273196551"/>
<marker id="1273196552"/>
<marker id="1273196553"/>
<marker id="1273196554"/>
<marker id="1273196555"/>
<marker id="1273196556"/>
<marker id="1273196557"/>
<marker id="1273196558"/>
<marker id="1273196559"/>
<marker id="1273196560"/>
<marker id="1273196561"/>
<marker id="1273196562"/>
<marker id="1273196563"/>
<marker id="1273196564"/>
<marker id="1273196565"/>
<marker id="1273196566"/>
<marker id="1273196567"/>
<marker id="1273196568"/>
<marker id="1273196569"/>
<marker id="1273196570"/>
<marker id="1273196571"/>
<marker id="1273196572"/>
<marker id="1273196573"/>
<marker id="1273196574"/>
<marker id="1273196575"/>
<marker id="1273196576"/>
<marker id="1273196577"/>
<marker id="1273196578"/>
<marker id="1273196579"/>
<marker id="1273196580"/>
<marker id="1273196581"/>
<marker id="1273196582"/>
<marker id="1273196583"/>
<marker id="1273196592"/>
<marker id="1273253888"/>
<marker id="1273257984"/>
<marker id="1273257985"/>
<marker id="1273257986"/>
<marker id="1273257987"/>
<marker id="1273257990"/>
<marker id="1273262080"/>
<marker id="1273262081"/>
<marker id="1273262082"/>
<marker id="1273262083"/>
<marker id="1273262084"/>
<marker id="1273262085"/>
<marker id="1273262086"/>
<marker id="1273262087"/>
<marker id="1273262088"/>
<marker id="1273262097"/>
<marker id="1273262098"/>
<marker id="1273262099"/>
<marker id="1273262100"/>
<marker id="1273262101"/>
<marker id="1273262102"/>
<marker id="1273262103"/>
<marker id="1273262104"/>
<marker id="1273262105"/>
<marker id="1273262106"/>
<marker id="1273262107"/>
<marker id="1273262144"/>
<marker id="1273262145"/>
<marker id="1273262146"/>
<marker id="1273262147"/>
<marker id="1273262148"/>
<marker id="1273262149"/>
<marker id="1273262150"/>
<marker id="1273262151"/>
<marker id="1273266176"/>
<marker id="1273266177"/>
<marker id="1273266178"/>
<marker id="1273266180"/>
<marker id="1273266181"/>
<marker id="1273266182"/>
<marker id="1273266183"/>
<marker id="1273266184"/>
<marker id="1273266185"/>
<marker id="1273266186"/>
<marker id="1273266187"/>
<marker id="1273266188"/>
<marker id="1273266189"/>
<marker id="1273323520"/>
<marker id="1273323534"/>
<marker id="1273323535"/>
<marker id="1273323536"/>
<marker id="1273323537"/>
<marker id="1273323538"/>
<marker id="1273323539"/>
<marker id="1273323540"/>
<marker id="1273323552"/>
<marker id="1273323553"/>
<marker id="1273323554"/>
<marker id="1273323555"/>
<marker id="1273323556"/>
<marker id="1273323557"/>
<marker id="1273323558"/>
<marker id="1273323559"/>
<marker id="1273323560"/>
<marker id="1273323561"/>
<marker id="1273323562"/>
<marker id="1273323563"/>
<marker id="1273323564"/>
<marker id="1273327616"/>
</index>
