<?xml version="1.0" encoding="UTF-8"?><index key="268435466">
<marker id="284246041"/>
<marker id="284246042"/>
<marker id="284246043"/>
<marker id="284246044"/>
<marker id="284246045"/>
<marker id="284246046"/>
<marker id="284246047"/>
<marker id="284246048"/>
<marker id="284246049"/>
<marker id="284246050"/>
<marker id="284246051"/>
<marker id="284246052"/>
<marker id="284246053"/>
<marker id="284246054"/>
<marker id="284246055"/>
<marker id="284246056"/>
<marker id="284246057"/>
<marker id="284246058"/>
<marker id="284246059"/>
<marker id="284246060"/>
<marker id="284246061"/>
<marker id="284246062"/>
<marker id="284246063"/>
<marker id="284246064"/>
<marker id="284246065"/>
<marker id="284246066"/>
<marker id="284246067"/>
<marker id="284246068"/>
<marker id="284246069"/>
<marker id="284246070"/>
<marker id="284246071"/>
<marker id="284246072"/>
<marker id="284246073"/>
<marker id="284246074"/>
<marker id="284246075"/>
<marker id="284246076"/>
<marker id="284246077"/>
<marker id="284246078"/>
<marker id="284246079"/>
<marker id="284246080"/>
<marker id="284246081"/>
<marker id="284246082"/>
<marker id="284246083"/>
<marker id="284246084"/>
<marker id="284246085"/>
<marker id="284246086"/>
<marker id="284246087"/>
<marker id="284246088"/>
<marker id="284246089"/>
<marker id="284246090"/>
<marker id="284246091"/>
<marker id="284246092"/>
<marker id="284246093"/>
<marker id="284246094"/>
<marker id="284246095"/>
<marker id="284246096"/>
<marker id="284246097"/>
<marker id="284246098"/>
<marker id="284246099"/>
<marker id="284246100"/>
<marker id="284246101"/>
<marker id="284246102"/>
<marker id="284246103"/>
<marker id="284246104"/>
<marker id="284246105"/>
<marker id="284246106"/>
<marker id="284246107"/>
<marker id="284246108"/>
<marker id="284246109"/>
<marker id="284246110"/>
<marker id="284246111"/>
<marker id="284246112"/>
<marker id="284246113"/>
<marker id="284246114"/>
<marker id="284246115"/>
<marker id="284246116"/>
<marker id="284246117"/>
<marker id="284246118"/>
<marker id="284246119"/>
<marker id="284246120"/>
<marker id="284246121"/>
<marker id="284246122"/>
<marker id="284246123"/>
<marker id="284246124"/>
<marker id="284246125"/>
<marker id="284246126"/>
<marker id="284246127"/>
<marker id="284246128"/>
<marker id="284246129"/>
<marker id="284246130"/>
<marker id="284246131"/>
<marker id="284246132"/>
<marker id="284246133"/>
<marker id="284246134"/>
<marker id="284246135"/>
<marker id="284246136"/>
<marker id="284246137"/>
<marker id="284246138"/>
<marker id="284246139"/>
<marker id="284246140"/>
<marker id="284246141"/>
<marker id="284246142"/>
<marker id="284246143"/>
<marker id="284246144"/>
<marker id="284246145"/>
<marker id="284246146"/>
<marker id="284246147"/>
<marker id="284246148"/>
<marker id="284246150"/>
<marker id="284246151"/>
<marker id="284246155"/>
<marker id="284246156"/>
<marker id="284246157"/>
<marker id="284246158"/>
<marker id="284246159"/>
<marker id="284246160"/>
<marker id="284246161"/>
<marker id="284246162"/>
<marker id="284246163"/>
<marker id="284246164"/>
<marker id="284246165"/>
<marker id="284246166"/>
<marker id="284246167"/>
<marker id="284246168"/>
<marker id="284246169"/>
<marker id="284246170"/>
<marker id="284246171"/>
<marker id="284246172"/>
<marker id="284246173"/>
<marker id="284246174"/>
<marker id="284246175"/>
<marker id="284246176"/>
<marker id="284246177"/>
<marker id="284246178"/>
<marker id="284246179"/>
<marker id="284246180"/>
<marker id="284246181"/>
<marker id="284246182"/>
<marker id="284246183"/>
<marker id="284246184"/>
<marker id="284246185"/>
<marker id="284246186"/>
<marker id="284246187"/>
<marker id="284246188"/>
<marker id="284246189"/>
<marker id="284246190"/>
<marker id="284246191"/>
<marker id="284246192"/>
<marker id="284246193"/>
<marker id="284246194"/>
<marker id="284246195"/>
<marker id="284246196"/>
<marker id="284246197"/>
<marker id="284246198"/>
<marker id="284246199"/>
<marker id="284246200"/>
<marker id="284246201"/>
<marker id="284246202"/>
<marker id="284246203"/>
<marker id="284246204"/>
<marker id="284246205"/>
<marker id="284246206"/>
<marker id="284246207"/>
<marker id="284246211"/>
<marker id="524988463"/>
<marker id="524988464"/>
<marker id="524988465"/>
<marker id="524988466"/>
<marker id="524988467"/>
<marker id="524988468"/>
<marker id="524988469"/>
<marker id="524988470"/>
<marker id="524988471"/>
<marker id="524988472"/>
<marker id="524988473"/>
<marker id="524988474"/>
<marker id="524988478"/>
<marker id="524988479"/>
<marker id="524988480"/>
<marker id="524988481"/>
<marker id="524988482"/>
<marker id="524988483"/>
<marker id="524988484"/>
<marker id="524988485"/>
<marker id="524988486"/>
<marker id="524988487"/>
<marker id="524988488"/>
<marker id="524988489"/>
<marker id="524988490"/>
<marker id="524988491"/>
<marker id="524988492"/>
<marker id="524988493"/>
<marker id="524988494"/>
<marker id="524988495"/>
<marker id="524988496"/>
<marker id="524988497"/>
<marker id="524988498"/>
<marker id="524988499"/>
<marker id="524988500"/>
<marker id="524988501"/>
<marker id="524988502"/>
<marker id="524988503"/>
<marker id="524988504"/>
<marker id="524988505"/>
<marker id="524988506"/>
<marker id="524988507"/>
<marker id="524988508"/>
<marker id="524988509"/>
<marker id="524988510"/>
<marker id="524988511"/>
<marker id="524988512"/>
<marker id="524988513"/>
<marker id="524988514"/>
<marker id="524988515"/>
<marker id="524988516"/>
<marker id="524988517"/>
<marker id="524988518"/>
<marker id="524988519"/>
<marker id="524988520"/>
<marker id="524988521"/>
<marker id="524988522"/>
<marker id="524988523"/>
<marker id="524988524"/>
<marker id="524988525"/>
<marker id="524988526"/>
<marker id="524988527"/>
<marker id="524988528"/>
<marker id="524988529"/>
<marker id="524988530"/>
<marker id="524988531"/>
<marker id="524988532"/>
<marker id="524988533"/>
<marker id="524988534"/>
<marker id="524988536"/>
<marker id="524988537"/>
<marker id="524988538"/>
<marker id="524988539"/>
<marker id="524988540"/>
<marker id="524988544"/>
<marker id="524988545"/>
<marker id="524988546"/>
<marker id="524988547"/>
<marker id="524988548"/>
<marker id="524988549"/>
<marker id="524988550"/>
<marker id="524988551"/>
<marker id="524988552"/>
<marker id="524988553"/>
<marker id="524988554"/>
<marker id="524988555"/>
<marker id="524988556"/>
<marker id="524988557"/>
<marker id="524988558"/>
<marker id="524988559"/>
<marker id="524988560"/>
<marker id="524988561"/>
<marker id="524988562"/>
<marker id="524988563"/>
<marker id="524988564"/>
<marker id="524988565"/>
<marker id="524988566"/>
<marker id="524988567"/>
<marker id="524988568"/>
<marker id="524988569"/>
<marker id="524988570"/>
<marker id="524988571"/>
<marker id="524988572"/>
<marker id="524988573"/>
<marker id="524988574"/>
<marker id="524988575"/>
<marker id="524988576"/>
<marker id="524988577"/>
<marker id="524988578"/>
<marker id="524988579"/>
<marker id="524988580"/>
<marker id="524988581"/>
<marker id="524988582"/>
<marker id="524988583"/>
<marker id="524988584"/>
<marker id="524988585"/>
<marker id="524988586"/>
<marker id="524988587"/>
<marker id="524988588"/>
<marker id="524988589"/>
<marker id="524988590"/>
<marker id="524988591"/>
<marker id="524988592"/>
<marker id="524988593"/>
<marker id="524988594"/>
<marker id="524988595"/>
<marker id="524988596"/>
<marker id="524988597"/>
<marker id="524988598"/>
<marker id="524988599"/>
<marker id="524988600"/>
<marker id="524988601"/>
<marker id="524988602"/>
<marker id="524988603"/>
<marker id="524988604"/>
<marker id="524988605"/>
<marker id="524988606"/>
<marker id="524988607"/>
<marker id="524988608"/>
<marker id="524988609"/>
<marker id="524988610"/>
<marker id="524988611"/>
<marker id="524988612"/>
<marker id="524988613"/>
<marker id="524988614"/>
<marker id="524988615"/>
<marker id="524988616"/>
<marker id="524988617"/>
<marker id="524988618"/>
<marker id="524988619"/>
<marker id="524988622"/>
<marker id="524988623"/>
</index>
