<?xml version="1.0" encoding="UTF-8"?><index key="1879256516">
<marker id="525135884"/>
<marker id="525135889"/>
<marker id="525135891"/>
<marker id="525135892"/>
<marker id="525135894"/>
<marker id="525135895"/>
<marker id="525135896"/>
<marker id="525135898"/>
<marker id="525135904"/>
<marker id="525135905"/>
<marker id="525135907"/>
<marker id="525135908"/>
<marker id="525135909"/>
<marker id="525135910"/>
<marker id="525135911"/>
<marker id="525135912"/>
<marker id="525135913"/>
<marker id="525135915"/>
<marker id="525135917"/>
<marker id="525135918"/>
<marker id="525135929"/>
<marker id="525135944"/>
<marker id="525135951"/>
<marker id="525135952"/>
<marker id="525135953"/>
<marker id="525135954"/>
<marker id="525135955"/>
<marker id="525135956"/>
<marker id="525135957"/>
<marker id="525135958"/>
<marker id="525135960"/>
<marker id="525135961"/>
<marker id="525135962"/>
<marker id="525135975"/>
<marker id="525135977"/>
<marker id="525135987"/>
<marker id="525135989"/>
<marker id="525135999"/>
<marker id="525136003"/>
<marker id="525136014"/>
<marker id="525136015"/>
<marker id="525136016"/>
<marker id="525136017"/>
<marker id="525136018"/>
<marker id="525136019"/>
<marker id="525136020"/>
<marker id="525136021"/>
<marker id="525136023"/>
<marker id="525136060"/>
<marker id="525136061"/>
</index>
