<?xml version="1.0" encoding="UTF-8"?><index key="1879138594">
<marker id="805232640"/>
<marker id="805232641"/>
<marker id="805232642"/>
<marker id="805232644"/>
<marker id="805232647"/>
<marker id="805232648"/>
<marker id="805232649"/>
<marker id="805232650"/>
<marker id="805232651"/>
<marker id="805232652"/>
<marker id="805232653"/>
<marker id="805232654"/>
<marker id="805232709"/>
<marker id="805232710"/>
<marker id="805232711"/>
<marker id="805232712"/>
<marker id="805232713"/>
<marker id="805232714"/>
<marker id="805232715"/>
<marker id="805232732"/>
<marker id="805232733"/>
<marker id="805232734"/>
<marker id="805232735"/>
<marker id="805232736"/>
<marker id="805232737"/>
<marker id="805232739"/>
<marker id="805232740"/>
<marker id="805232741"/>
<marker id="805232742"/>
<marker id="805232743"/>
<marker id="805232744"/>
<marker id="805232745"/>
<marker id="805232746"/>
<marker id="805232747"/>
<marker id="805232748"/>
<marker id="805232749"/>
<marker id="805232750"/>
<marker id="805232751"/>
<marker id="805232752"/>
<marker id="805232753"/>
<marker id="805232754"/>
<marker id="805232755"/>
<marker id="805232756"/>
<marker id="805232757"/>
<marker id="805232758"/>
<marker id="805232759"/>
<marker id="805232760"/>
<marker id="805232761"/>
<marker id="805232762"/>
<marker id="805232763"/>
<marker id="805232764"/>
<marker id="805232765"/>
<marker id="805232766"/>
<marker id="805232767"/>
<marker id="805232768"/>
<marker id="805232769"/>
<marker id="805232770"/>
<marker id="805232771"/>
<marker id="805232791"/>
<marker id="805232793"/>
<marker id="805232794"/>
<marker id="805232795"/>
<marker id="805232796"/>
<marker id="805232797"/>
<marker id="805232798"/>
<marker id="805232799"/>
<marker id="805232800"/>
<marker id="805232801"/>
<marker id="805232802"/>
<marker id="805232803"/>
<marker id="805232804"/>
<marker id="805232805"/>
<marker id="805232806"/>
<marker id="805232807"/>
<marker id="805232808"/>
<marker id="805232809"/>
<marker id="805232810"/>
<marker id="805232811"/>
<marker id="805232812"/>
<marker id="805232813"/>
<marker id="805232814"/>
<marker id="805232815"/>
<marker id="805232816"/>
<marker id="805232817"/>
<marker id="805232818"/>
<marker id="805232819"/>
<marker id="805232820"/>
<marker id="805232821"/>
<marker id="805232822"/>
<marker id="805232823"/>
<marker id="805232824"/>
<marker id="805232825"/>
<marker id="805232826"/>
<marker id="805232827"/>
<marker id="805232828"/>
<marker id="805232829"/>
<marker id="805232830"/>
<marker id="805232831"/>
<marker id="805232832"/>
<marker id="805232833"/>
<marker id="805232834"/>
<marker id="805232835"/>
<marker id="805232836"/>
<marker id="805232837"/>
<marker id="805232838"/>
<marker id="805232839"/>
<marker id="805232840"/>
<marker id="805232841"/>
<marker id="805232842"/>
<marker id="805232843"/>
<marker id="805232844"/>
<marker id="805232845"/>
<marker id="805232846"/>
<marker id="805232847"/>
<marker id="805232848"/>
<marker id="805232849"/>
<marker id="805232850"/>
<marker id="805232853"/>
<marker id="805232854"/>
<marker id="805232855"/>
<marker id="805232856"/>
<marker id="805232857"/>
<marker id="805232858"/>
<marker id="805232859"/>
<marker id="805232860"/>
<marker id="805232861"/>
<marker id="805232866"/>
<marker id="805232867"/>
<marker id="805232868"/>
<marker id="805232869"/>
<marker id="805232870"/>
<marker id="805232871"/>
<marker id="805232880"/>
<marker id="805232881"/>
<marker id="805232882"/>
<marker id="805232883"/>
<marker id="805232884"/>
<marker id="805232885"/>
<marker id="805232886"/>
<marker id="805232887"/>
<marker id="805232888"/>
<marker id="805232889"/>
<marker id="805232890"/>
<marker id="805232891"/>
<marker id="805232892"/>
<marker id="805232893"/>
<marker id="805232894"/>
<marker id="805232895"/>
<marker id="805232896"/>
<marker id="805232897"/>
<marker id="805232898"/>
<marker id="805232899"/>
<marker id="805232900"/>
<marker id="805232901"/>
<marker id="805232902"/>
<marker id="805232903"/>
<marker id="805232904"/>
<marker id="805232905"/>
<marker id="805232906"/>
<marker id="805232907"/>
<marker id="805232908"/>
<marker id="805232909"/>
<marker id="805232910"/>
<marker id="805232911"/>
<marker id="805232912"/>
<marker id="805232913"/>
<marker id="805232914"/>
<marker id="805232915"/>
<marker id="805232916"/>
<marker id="805232917"/>
<marker id="805232918"/>
<marker id="805232919"/>
<marker id="805232920"/>
<marker id="805232921"/>
<marker id="805232922"/>
<marker id="805232923"/>
<marker id="805232924"/>
<marker id="805232925"/>
<marker id="805232926"/>
<marker id="805232927"/>
<marker id="805232928"/>
<marker id="805232929"/>
<marker id="805232930"/>
<marker id="805232931"/>
<marker id="805232932"/>
<marker id="805232933"/>
<marker id="805232934"/>
<marker id="805232935"/>
<marker id="805232936"/>
<marker id="805232937"/>
<marker id="805232938"/>
<marker id="805232939"/>
<marker id="805232940"/>
<marker id="805232941"/>
<marker id="805232942"/>
<marker id="805232943"/>
<marker id="805232944"/>
<marker id="805232945"/>
<marker id="805232946"/>
<marker id="805232947"/>
<marker id="805232948"/>
<marker id="805232949"/>
<marker id="805232950"/>
<marker id="805232951"/>
<marker id="805232964"/>
<marker id="805232966"/>
<marker id="805232970"/>
<marker id="805232971"/>
<marker id="805232972"/>
<marker id="805232973"/>
<marker id="805232974"/>
<marker id="805232975"/>
<marker id="805232976"/>
<marker id="805232977"/>
<marker id="805232981"/>
<marker id="805232982"/>
<marker id="805232983"/>
<marker id="805232984"/>
<marker id="805232985"/>
<marker id="805232986"/>
<marker id="805232987"/>
<marker id="805232988"/>
<marker id="805232989"/>
<marker id="805232993"/>
<marker id="805232994"/>
<marker id="805232995"/>
<marker id="805232996"/>
<marker id="805232997"/>
<marker id="805232998"/>
<marker id="805232999"/>
<marker id="805233000"/>
</index>
